README.md
setup.cfg
setup.py
yaledirectory/__init__.py
yaledirectory/main.py
yaledirectory.egg-info/PKG-INFO
yaledirectory.egg-info/SOURCES.txt
yaledirectory.egg-info/dependency_links.txt
yaledirectory.egg-info/requires.txt
yaledirectory.egg-info/top_level.txt