Metadata-Version: 1.0
Name: yaledirectory
Version: 1.0.0
Summary: Library for fetching data from the Yale Directory API.
Home-page: https://github.com/ErikBoesen/yaledirectory
Author: Erik Boesen
Author-email: me@erikboesen.com
License: GPL
Platform: UNKNOWN
